Workbook

Sheet README
A1: Retention Investment Scenario Model
A2: Source: E-Commerce Customer Intelligence & LTV Engine (this repository). Data: UCI Online Retail II, 1 Dec 2009 – 9 Dec 2011.
A4: HOW TO USE
A5: 1. Edit ONLY yellow cells (blue text) on the 'Assumptions' and 'Scenario' sheets.
A6: 2. All other numbers are formulas and update automatically.
A8: WHAT IS CALCULATED vs ASSUMED
A9: CALCULATED from data: customers, trailing-12m revenue, revenue at risk (= trailing-12m revenue x modelled 12-month churn probability).
A10: ASSUMED (placeholders — replace with company figures): gross margin, save rate per segment, cost per contact. The dataset contains no cost, margin or campaign data.
A12: LIMITATIONS
A13: Revenue at risk is an exposure measure, not a loss forecast. It excludes spend decline by customers who stay (net revenue retention was 81%), so the true retention opportunity is larger.
A14: Customer metrics cover identified customers only (~85% of merchandise revenue).
A15: Save rates are hypotheses to be TESTED (hold-out control group), not facts.

Sheet Assumptions
A1: Assumption | B1: Value | C1: Note
A2: Gross margin (%) | B2: 0.4 | C2: ASSUMPTION — not in data. Replace with Finance's gross margin.
A3: Programme overhead (£, fixed) | B3: 5000 | C3: ASSUMPTION — set-up cost (CRM configuration, analyst time).

Sheet Scenario
A1: Management segment | B1: Customers | C1: Trailing-12m revenue (£) | D1: Revenue at risk (£) | E1: Save rate (assumption) | F1: Accounts contacted | G1: Cost per contact (£, assumption) | H1: Recovered revenue (£) | I1: Recovered gross profit (£) | J1: Programme cost (£) | K1: Net benefit (£) | L1: ROI (x)
A2: 1. Protect - Key Accounts | B2: 710 | C2: 5240557.4 | D2: 174849.87 | E2: 0.1 | F2: =B2 -> 710 | G2: 40 | H2: =D2*E2 -> 17484.987 | I2: =H2*Assumptions!$B$2 -> 6993.9948 | J2: =F2*G2 -> 28400 | K2: =I2-J2 -> -21406.005 | L2: =IF(J2=0,"n/a",K2/J2) -> -0.75373258
A3: 2. Rescue - High Value at Risk | B3: 107 | C3: 472453.71 | D3: 91536.36 | E3: 0.25 | F3: =B3 -> 107 | G3: 40 | H3: =D3*E3 -> 22884.09 | I3: =H3*Assumptions!$B$2 -> 9153.636 | J3: =F3*G3 -> 4280 | K3: =I3-J3 -> 4873.636 | L3: =IF(J3=0,"n/a",K3/J3) -> 1.1387
A4: 3. Develop - Core Growth | B4: 1020 | C4: 1194878.2 | D4: 217267.61 | E4: 0.1 | F4: =B4 -> 1020 | G4: 2 | H4: =D4*E4 -> 21726.761 | I4: =H4*Assumptions!$B$2 -> 8690.7044 | J4: =F4*G4 -> 2040 | K4: =I4-J4 -> 6650.7044 | L4: =IF(J4=0,"n/a",K4/J4) -> 3.2601492
A5: 4. Win Back - Core at Risk | B5: 108 | C5: 112918.24 | D5: 53555.93 | E5: 0.15 | F5: =B5 -> 108 | G5: 2 | H5: =D5*E5 -> 8033.3895 | I5: =H5*Assumptions!$B$2 -> 3213.3558 | J5: =F5*G5 -> 216 | K5: =I5-J5 -> 2997.3558 | L5: =IF(J5=0,"n/a",K5/J5) -> 13.876647
A6: 5. Nurture - New Customers | B6: 591 | C6: 379899.44 | D6: 112702.9 | E6: 0.1 | F6: =B6 -> 591 | G6: 2 | H6: =D6*E6 -> 11270.29 | I6: =H6*Assumptions!$B$2 -> 4508.116 | J6: =F6*G6 -> 1182 | K6: =I6-J6 -> 3326.116 | L6: =IF(J6=0,"n/a",K6/J6) -> 2.8139729
A7: 6. Automate - Low Value Active | B7: 834 | C7: 324205.87 | D7: 106920.3 | E7: 0.05 | F7: =B7 -> 834 | G7: 0.5 | H7: =D7*E7 -> 5346.015 | I7: =H7*Assumptions!$B$2 -> 2138.406 | J7: =F7*G7 -> 417 | K7: =I7-J7 -> 1721.406 | L7: =IF(J7=0,"n/a",K7/J7) -> 4.1280719
A8: 7. Deprioritise - Low Value Lapsing | B8: 880 | C8: 208638.46 | D8: 130488.67 | E8: 0.03 | F8: =B8 -> 880 | G8: 0.5 | H8: =D8*E8 -> 3914.6601 | I8: =H8*Assumptions!$B$2 -> 1565.864 | J8: =F8*G8 -> 440 | K8: =I8-J8 -> 1125.864 | L8: =IF(J8=0,"n/a",K8/J8) -> 2.5587819
A9: Total (before overhead) | B9: =SUM(B2:B8) -> 4250 | C9: =SUM(C2:C8) -> 7933551.3 | D9: =SUM(D2:D8) -> 887321.64 | F9: =SUM(F2:F8) -> 4250 | H9: =SUM(H2:H8) -> 90660.193 | I9: =SUM(I2:I8) -> 36264.077 | J9: =SUM(J2:J8) -> 36975 | K9: =SUM(K2:K8) -> -710.92296
A10: Less: programme overhead | K10: =-Assumptions!B3 -> -5000
A11: Net benefit after overhead | K11: =K9+K10 -> -5710.923
A12: Break-even save rate, Rescue segment | E12: =IF(D3*Assumptions!$B$2=0,"n/a",J3/(D3*Assumptions!$B$2)) -> 0.11689344 | F12: <- save rate at which Rescue outreach pays for itself

Sheet KPI_Summary
A1: KPI (identified + guest unless stated) | B1: FY2010 (Dec09–Nov10) | C1: FY2011 (Dec10–Nov11) | D1: Change
A2: Net merchandise revenue (£) | B2: 9146264.7 | C2: 9299896.3 | D2: =IF(B2=0,"n/a",C2/B2-1) -> 0.016797188
A3: Identified-customer sales (£) | B3: 8175241.2 | C3: 7969516.9 | D3: =IF(B3=0,"n/a",C3/B3-1) -> -0.025164311
A4: Guest sales (£) | B4: 1065287.2 | C4: 1407728.8 | D4: =IF(B4=0,"n/a",C4/B4-1) -> 0.32145473
A5: Active identified customers | B5: 4227 | C5: 4284 | D5: =IF(B5=0,"n/a",C5/B5-1) -> 0.013484741
A6: Orders per customer | B6: 4.273 | C6: 4.087 | D6: =IF(B6=0,"n/a",C6/B6-1) -> -0.043529136
A7: AOV, identified (£) | B7: 452.67 | C7: 455.17 | D7: =IF(B7=0,"n/a",C7/B7-1) -> 0.005522787
A8: Return rate | B8: 0.0102 | C8: 0.0082 | D8: =IF(B8=0,"n/a",C8/B8-1) -> -0.19607843
A10: Customer retention FY10→FY11 | B10: 0.6385
A11: Net revenue retention FY10→FY11 | B11: 0.8081
A13: Source: reports/tables/sql_kpi_fy_comparison.csv, sql_kpi_yoy_retention.csv (calculated from data)

Sheet Rescue_Call_List
A1: Priority Rank | B1: Customer Id | C1: Country | D1: Revenue T12M | E1: Churn Prob 12M | F1: Revenue At Risk | G1: Clv 12M | H1: Recency Days | I1: Avg Gap Days | J1: Cadence Status | K1: At Risk Reason | L1: Rfm Segment
A2: 1 | B2: 16029 | C2: United Kingdom | D2: 56098.41 | E2: 0.048599189 | F2: 2726.3372 | G2: 37853.404 | H2: 39 | I2: 6.8 | J2: Lapsed | K2: Overdue vs own buying cadence | L2: Loyal Customers
A3: 2 | B3: 15749 | C3: United Kingdom | D3: 21535.9 | E3: 0.26517233 | F3: 5710.7247 | G3: 11744.105 | H3: 236 | I3: 97 | J3: Insufficient history | K3: Elevated churn probability | L3: Hibernating
A4: 3 | B4: 15513 | C4: United Kingdom | D4: 13206.58 | E4: 0.045788644 | F4: 604.71139 | G4: 10895.95 | H4: 32 | I4: 19.5 | J4: Slipping | K4: Overdue vs own buying cadence | L4: Loyal Customers
A5: 4 | B5: 12939 | C5: United Kingdom | D5: 11581.8 | E5: 0.090499331 | F5: 1048.1452 | G5: 10576.773 | H5: 65 | I5: 33.3 | J5: Slipping | K5: Overdue vs own buying cadence | L5: Loyal Customers
A6: 5 | B6: 16180 | C6: United Kingdom | D6: 10217.48 | E6: 0.19629719 | F6: 2005.6626 | G6: 7374.7816 | H6: 101 | I6: 36.2 | J6: Slipping | K6: Overdue vs own buying cadence | L6: Loyal Customers
A7: 6 | B7: 17865 | C7: United Kingdom | D7: 10200.59 | E7: 0.04247504 | F7: 433.27046 | G7: 10637.39 | H7: 31 | I7: 16.1 | J7: Slipping | K7: Overdue vs own buying cadence | L7: Loyal Customers
A8: 7 | B8: 16843 | C8: United Kingdom | D8: 10183.82 | E8: 0.061186778 | F8: 623.11514 | G8: 7924.9105 | H8: 43 | I8: 20.8 | J8: Slipping | K8: Overdue vs own buying cadence | L8: Loyal Customers
A9: 8 | B9: 12590 | C9: Germany | D9: 9338.38 | E9: 0.36230746 | F9: 3383.3648 | G9: 315.92709 | H9: 191 | J9: Insufficient history | K9: Elevated churn probability | L9: Hibernating
A10: 9 | B10: 14952 | C10: United Kingdom | D10: 8015.79 | E10: 0.075923445 | F10: 608.58639 | G10: 7119.6288 | H10: 47 | I10: 21.8 | J10: Slipping | K10: Overdue vs own buying cadence | L10: Loyal Customers
A11: 10 | B11: 16745 | C11: United Kingdom | D11: 7157.1 | E11: 0.1811468 | F11: 1296.4858 | G11: 4221.9888 | H11: 87 | I11: 14.1 | J11: Lapsed | K11: Overdue vs own buying cadence | L11: Loyal Customers
A12: 11 | B12: 12980 | C12: United Kingdom | D12: 7092.06 | E12: 0.32009555 | F12: 2270.1369 | G12: 4453.4976 | H12: 156 | I12: 29 | J12: Lapsed | K12: Elevated probability + overdue on cadence | L12: Loyal Customers
A13: 12 | B13: 16729 | C13: United Kingdom | D13: 7045.41 | E13: 0.086813443 | F13: 611.6363 | G13: 7001.4958 | H13: 37 | I13: 10.2 | J13: Lapsed | K13: Overdue vs own buying cadence | L13: Loyal Customers
A14: 13 | B14: 13093 | C14: United Kingdom | D14: 6942.07 | E14: 0.48948388 | F14: 3398.0314 | G14: 0.12885929 | H14: 268 | I14: 8.5 | J14: Lapsed | K14: Elevated probability + overdue on cadence | L14: Cannot Lose Them
A15: 14 | B15: 13027 | C15: United Kingdom | D15: 6912 | E15: 0.21165691 | F15: 1462.9726 | G15: 6680.0887 | H15: 114 | I15: 31.9 | J15: Lapsed | K15: Overdue vs own buying cadence | L15: Loyal Customers
A16: 15 | B16: 16187 | C16: United Kingdom | D16: 6841.24 | E16: 0.060961039 | F16: 417.0491 | G16: 5854.8103 | H16: 32 | I16: 18.1 | J16: Slipping | K16: Overdue vs own buying cadence | L16: Loyal Customers
A17: 16 | B17: 16652 | C17: United Kingdom | D17: 6654.26 | E17: 0.094634438 | F17: 629.72216 | G17: 7460.698 | H17: 54 | I17: 38.3 | J17: Slipping | K17: Overdue vs own buying cadence | L17: Loyal Customers
A18: 17 | B18: 15939 | C18: United Kingdom | D18: 6087.26 | E18: 0.16614938 | F18: 1011.3944 | G18: 4096.7309 | H18: 90 | I18: 20.4 | J18: Lapsed | K18: Overdue vs own buying cadence | L18: Loyal Customers
A19: 18 | B19: 14101 | C19: United Kingdom | D19: 5976.79 | E19: 0.1160081 | F19: 693.35607 | G19: 4466.4059 | H19: 74 | I19: 45.7 | J19: Slipping | K19: Overdue vs own buying cadence | L19: Loyal Customers
A20: 19 | B20: 12637 | C20: France | D20: 5790.25 | E20: 0.094932052 | F20: 549.68031 | G20: 4013.7087 | H20: 68 | I20: 43.3 | J20: Slipping | K20: Overdue vs own buying cadence | L20: Loyal Customers
A21: 20 | B21: 16553 | C21: United Kingdom | D21: 5668.82 | E21: 0.32202408 | F21: 1825.4965 | G21: 5412.0965 | H21: 164 | I21: 15.7 | J21: Lapsed | K21: Elevated probability + overdue on cadence | L21: Loyal Customers
... A24: 23 | B24: 17061 | C24: United Kingdom | D24: 5116.13 | E24: 0.1942256 | F24: 993.68341 | G24: 3458.3272 | H24: 74 | I24: 15.9 | J24: Lapsed | K24: Overdue vs own buying cadence | L24: Loyal Customers
A25: 24 | B25: 12688 | C25: Israel | D25: 4873.81 | E25: 0.3937231 | F25: 1918.9316 | G25: 482.41248 | H25: 114 | J25: Insufficient history | K25: Elevated churn probability | L25: About to Sleep
A26: 25 | B26: 15874 | C26: United Kingdom | D26: 4346.57 | E26: 0.10029082 | F26: 435.92108 | G26: 4633.9515 | H26: 64 | I26: 31.9 | J26: Slipping | K26: Overdue vs own buying cadence | L26: Loyal Customers
A27: 26 | B27: 15301 | C27: United Kingdom | D27: 4334.35 | E27: 0.085637949 | F27: 371.18484 | G27: 4147.0135 | H27: 51 | I27: 25 | J27: Slipping | K27: Overdue vs own buying cadence | L27: Loyal Customers
A28: 27 | B28: 14016 | C28: EIRE | D28: 4278.46 | E28: 0.21945429 | F28: 938.92641 | G28: 3980.3945 | H28: 155 | I28: 53.9 | J28: Lapsed | K28: Overdue vs own buying cadence | L28: Loyal Customers
A29: 28 | B29: 12378 | C29: Switzerland | D29: 4008.62 | E29: 0.37067267 | F29: 1485.8859 | G29: 1728.0385 | H29: 130 | I29: 433 | J29: Insufficient history | K29: Elevated churn probability | L29: About to Sleep
A30: 29 | B30: 13802 | C30: United Kingdom | D30: 3906.27 | E30: 0.23312063 | F30: 910.63212 | G30: 9344.1203 | H30: 139 | I30: 29.1 | J30: Lapsed | K30: Overdue vs own buying cadence | L30: Loyal Customers
A31: 30 | B31: 18073 | C31: United Kingdom | D31: 3846.74 | E31: 0.47053764 | F31: 1810.036 | G31: 1336.2196 | H31: 115 | I31: 7.5 | J31: Lapsed | K31: Elevated probability + overdue on cadence | L31: Loyal Customers
A32: 31 | B32: 14364 | C32: United Kingdom | D32: 3717.35 | E32: 0.34603627 | F32: 1286.3379 | G32: 2697.9903 | H32: 109 | I32: 14.7 | J32: Lapsed | K32: Elevated probability + overdue on cadence | L32: Loyal Customers
A33: 32 | B33: 14800 | C33: United Kingdom | D33: 3676.3 | E33: 0.079995785 | F33: 294.08851 | G33: 4396.4392 | H33: 48 | I33: 24.3 | J33: Slipping | K33: Overdue vs own buying cadence | L33: Loyal Customers
A34: 33 | B34: 15379 | C34: United Kingdom | D34: 3631.89 | E34: 0.31290332 | F34: 1136.4304 | G34: 1944.4042 | H34: 170 | I34: 33 | J34: Lapsed | K34: Elevated probability + overdue on cadence | L34: Loyal Customers
A35: 34 | B35: 13082 | C35: United Kingdom | D35: 3595.48 | E35: 0.26250723 | F35: 943.8395 | G35: 2879.6024 | H35: 127 | I35: 29.6 | J35: Lapsed | K35: Elevated probability + overdue on cadence | L35: Loyal Customers
A36: 35 | B36: 13552 | C36: United Kingdom | D36: 3539.53 | E36: 0.133571 | F36: 472.77856 | G36: 2866.1654 | H36: 67 | I36: 28.2 | J36: Slipping | K36: Overdue vs own buying cadence | L36: Loyal Customers
A37: 36 | B37: 15505 | C37: United Kingdom | D37: 3497.14 | E37: 0.17174265 | F37: 600.60808 | G37: 3760.0786 | H37: 53 | I37: 25.8 | J37: Slipping | K37: Overdue vs own buying cadence | L37: Loyal Customers
... A101: 100 | B101: 15235 | C101: United Kingdom | D101: 2082.46 | E101: 0.47237436 | F101: 983.7007 | G101: 102.42782 | H101: 218 | I101: 11.4 | J101: Lapsed | K101: Elevated probability + overdue on cadence | L101: Cannot Lose Them
